mammosunits/__init__.py
mammosunits-0.1.0.dist-info/LICENSE
mammosunits-0.1.0.dist-info/METADATA
mammosunits-0.1.0.dist-info/WHEEL
mammosunits-0.1.0.dist-info/top_level.txt
mammosunits-0.1.0.dist-info/RECORD
