Metadata-Version: 2.2
Name: mammosunits
Version: 0.1.0
Summary: Magnetic units package built on top of Astropy units
Author-email: Sam Holt <samjrholt@gmail.com>, Hans Fangohr <hans.fangohr@mpsd.mpg.de>
Requires-Python: >=3.11
License-File: LICENSE
Requires-Dist: astropy>=7.0.0
